{"id":"ENDcCZFjAW9h66eDoFg7I","title":"Seed","desc":"","updated":1654013219836,"created":1631921362276,"nav_exclude_children":true,"custom":{"nav_exclude_children":true},"fname":"seed","type":"note","vault":{"fsPath":"vault"},"contentHash":"de51ced1191ec49d23506124feb6e714","links":[{"type":"wiki","from":{"fname":"seed","id":"ENDcCZFjAW9h66eDoFg7I","vaultName":"vault"},"value":"seed.child","alias":"seed.child","position":{"start":{"line":5,"column":1,"offset":47},"end":{"line":5,"column":15,"offset":61},"indent":[]},"xvault":false,"sameFile":false,"to":{"fname":"seed.child"}}],"anchors":{},"children":["KboSDNpIShkOlDCJuWvZa"],"parent":"wn8PE1RhG0znK1alrGFYv","data":{}}
